pdfharvester/__init__.py
pdfharvester/get_keywords.py
pdfharvester/image_extractor.py
pdfharvester/pdfharvester.py
pdfharvester/table_extractor.py
pdfharvester-0.2.5.dist-info/METADATA
pdfharvester-0.2.5.dist-info/WHEEL
pdfharvester-0.2.5.dist-info/licenses/LICENSE
pdfharvester-0.2.5.dist-info/RECORD
