Metadata-Version: 2.1
Name: pdfharvester
Version: 0.2.5
Summary: A package for extracting tables and images from PDFs
Project-URL: Homepage, https://github.com/hashimputhiyakath/pdfharvester
Project-URL: Bug Tracker, https://github.com/hashimputhiyakath/pdfharvester/issues
Author-email: Hashim Puthiyakath <hashputhiyakath@gmail.com>
License: MIT License
License-File: LICENSE
Classifier: License :: OSI Approved :: MIT License
Classifier: Operating System :: OS Independent
Classifier: Programming Language :: Python :: 3
Requires-Python: >=3.7
Requires-Dist: pandas
Requires-Dist: pypdf2
Requires-Dist: textract
Requires-Dist: yake
